fhirpy_types_r4b/__init__.py
fhirpy_types_r4b/py.typed
fhirpy_types_r4b-0.1.1.dist-info/LICENSE
fhirpy_types_r4b-0.1.1.dist-info/METADATA
fhirpy_types_r4b-0.1.1.dist-info/WHEEL
fhirpy_types_r4b-0.1.1.dist-info/top_level.txt
fhirpy_types_r4b-0.1.1.dist-info/RECORD
