Metadata-Version: 2.1
Name: fhirpy_types_r4b
Version: 0.1.1
Summary: FHIR R4B pydantic models
Author-email: "beda.software" <fhirpy@beda.software>
Project-URL: Homepage, https://github.com/beda-software/fhir-py-types-r4b
Classifier: Programming Language :: Python :: 3
Classifier: Programming Language :: Python :: 3.11
Classifier: Programming Language :: Python :: 3.12
Classifier: License :: OSI Approved :: MIT License
Classifier: Operating System :: OS Independent
Requires-Python: >=3.11
License-File: LICENSE
Requires-Dist: pydantic >=2.9.0
